{
  "558388148171": [
    {
      "text": "Oi",
      "fromMe": false,
      "timestamp": "2026-01-24T13:59:45.407766"
    },
    {
      "text": "\u00c9 pra dar banho e colocar que roupa?",
      "fromMe": true,
      "timestamp": "2026-01-24T14:01:15.857302"
    },
    {
      "text": "Coloca uma camiseta",
      "fromMe": false,
      "timestamp": "2026-01-24T14:01:49.151902"
    },
    {
      "text": "Daquelas mesmo",
      "fromMe": false,
      "timestamp": "2026-01-24T14:01:54.912516"
    },
    {
      "text": "Eu vou mandar outra roupa",
      "fromMe": false,
      "timestamp": "2026-01-24T14:01:58.662435"
    },
    {
      "text": "Pra tua m\u00e3e vestir",
      "fromMe": false,
      "timestamp": "2026-01-24T14:02:02.218866"
    },
    {
      "text": "Nele",
      "fromMe": false,
      "timestamp": "2026-01-24T14:02:05.430548"
    }
  ],
  "5511998542266": [
    {
      "text": "Pior que t\u00f4 dirigindo mano",
      "fromMe": false,
      "timestamp": "2026-01-24T14:02:11.638112"
    },
    {
      "text": "Nem ouvi teus \u00e1udios ainda",
      "fromMe": false,
      "timestamp": "2026-01-24T14:02:17.122858"
    },
    {
      "text": "De boa mano",
      "fromMe": true,
      "timestamp": "2026-01-24T14:17:57.575511"
    }
  ],
  "558388042944": [
    {
      "text": "T\u00e1 certo hominho",
      "fromMe": false,
      "timestamp": "2026-01-24T14:05:15.028651"
    },
    {
      "text": "T\u00e1 bom hominho esse hor\u00e1rio",
      "fromMe": false,
      "timestamp": "2026-01-24T14:40:21.864148"
    }
  ],
  "120363298400068970@g.us": [
    {
      "text": "*Hugo Boss Bottled Night Eau De Toilette 100Ml*\n\n*\ud83d\udd25 R$\u00a0302,89* _em at\u00e9 5x_\n\n\ud83d\udecd\ufe0f *PEGAR PROMO\u00c7\u00c3O:*\nhttps://pincei.co/e/f356efad_8a\n\n\u26aa\ufe0f _Grupo Pincei Perfumes:_\nhttps://join.pincei.co/perfumes",
      "fromMe": false,
      "timestamp": "2026-01-24T14:22:18.656126"
    },
    {
      "text": "*Perfume David Beckham Instinct Eau de Parfum Masculino 50ml*\n\n*\ud83d\udd25 R$\u00a076,59*\n\n\ud83d\udecd\ufe0f *PEGAR PROMO\u00c7\u00c3O:*\nhttps://pincei.co/e/55726940_8a\n\n\u26aa\ufe0f _Grupo Pincei Perfumes:_\nhttps://join.pincei.co/perfumes",
      "fromMe": false,
      "timestamp": "2026-01-24T14:53:36.565187"
    }
  ],
  "558388046720": [
    {
      "text": "http://100.26.100.8/painel/",
      "fromMe": true,
      "timestamp": "2026-01-24T15:05:05.257202"
    },
    {
      "text": "http://100.26.100.8/painel/",
      "fromMe": true,
      "timestamp": "2026-01-24T15:07:05.908203"
    }
  ],
  "120363028717664713@g.us": [
    {
      "text": "Mais uma produ\u00e7\u00e3o que acabou de ficar pronta \ud83d\udd25\n\n*BALMAIN PARIS* \ud83e\udd29\nDispon\u00edvel em diversas cores \u2705",
      "fromMe": false,
      "timestamp": "2026-01-24T15:07:34.221926"
    }
  ],
  "558388911781": [
    {
      "text": "Eii mano",
      "fromMe": false,
      "timestamp": "2026-01-24T15:30:30.143313"
    },
    {
      "text": "Fala com Davyd a\u00ed",
      "fromMe": false,
      "timestamp": "2026-01-24T15:30:34.593618"
    },
    {
      "text": "Pra ver se dar certo",
      "fromMe": false,
      "timestamp": "2026-01-24T15:30:38.279523"
    },
    {
      "text": "Ele falou um hor\u00e1rio aqui a\u00ed tu conversa com ele",
      "fromMe": false,
      "timestamp": "2026-01-24T15:30:52.541352"
    },
    {
      "text": "Fala mano",
      "fromMe": true,
      "timestamp": "2026-01-24T16:22:54.322451"
    },
    {
      "text": "TO na correria aqui vei",
      "fromMe": true,
      "timestamp": "2026-01-24T16:22:58.648662"
    },
    {
      "text": "Mano Davyd falou CMG,ele disse que daria pra ele ir,s\u00f3 que ele iria sair do trabalho de 18 hrs,s\u00f3 que ele t\u00e1 sem dinheiro pra ir",
      "fromMe": false,
      "timestamp": "2026-01-24T16:26:38.564553"
    },
    {
      "text": "A\u00ed no caso teria que mandar antes dele ir",
      "fromMe": false,
      "timestamp": "2026-01-24T16:26:48.455043"
    },
    {
      "text": "Oq tu acha?",
      "fromMe": false,
      "timestamp": "2026-01-24T16:26:51.102881"
    }
  ],
  "558387033591": [
    {
      "text": "Boa tarde",
      "fromMe": false,
      "timestamp": "2026-01-24T15:36:35.007695"
    }
  ],
  "120363137678431404@g.us": [
    {
      "text": "BOA TARDA MINHA TROPA \ud83d\ude80",
      "fromMe": false,
      "timestamp": "2026-01-24T15:39:07.346484"
    }
  ],
  "558391146018": [
    {
      "text": "Deu certo?",
      "fromMe": true,
      "timestamp": "2026-01-24T16:08:12.991214"
    },
    {
      "text": "Deu sim viu",
      "fromMe": false,
      "timestamp": "2026-01-24T16:08:41.421435"
    },
    {
      "text": "Vinheram 4",
      "fromMe": false,
      "timestamp": "2026-01-24T16:08:51.313885"
    },
    {
      "text": "Coisa boa",
      "fromMe": true,
      "timestamp": "2026-01-24T16:10:23.630256"
    },
    {
      "text": "Que \u00f3timo que eles gostaram, ficamos muito felizes por isso!",
      "fromMe": false,
      "timestamp": "2026-01-24T16:18:43.182960"
    },
    {
      "text": "Vou avisar sim",
      "fromMe": false,
      "timestamp": "2026-01-24T16:18:46.317785"
    },
    {
      "text": "E muito obrigado pela a indica\u00e7\u00e3o",
      "fromMe": false,
      "timestamp": "2026-01-24T16:18:58.121101"
    }
  ],
  "558398051575": [
    {
      "text": "Tmj",
      "fromMe": true,
      "timestamp": "2026-01-24T16:08:21.923034"
    }
  ],
  "558387095009": [
    {
      "text": "Os meninos gostaram?",
      "fromMe": true,
      "timestamp": "2026-01-24T16:12:03.091475"
    },
    {
      "text": "E teu pai, gostou?",
      "fromMe": true,
      "timestamp": "2026-01-24T16:12:24.460739"
    }
  ],
  "120363420002148979@g.us": [
    {
      "text": "Cuida",
      "fromMe": false,
      "timestamp": "2026-01-24T16:19:18.914244"
    },
    {
      "text": "KKKKKKKKKK",
      "fromMe": false,
      "timestamp": "2026-01-24T16:24:36.083237"
    }
  ]
}